exasol/analytics/__init__.py
exasol/analytics/audit/audit.py
exasol/analytics/audit/audit_query_handler.py
exasol/analytics/audit/columns.py
exasol/analytics/lua/src/exasol_script_tools.lua
exasol/analytics/lua/src/query_handler_runner.lua
exasol/analytics/lua/src/query_handler_runner_main.lua
exasol/analytics/lua/src/query_loop.lua
exasol/analytics/lua/test/test_create_exa_env.lua
exasol/analytics/lua/test/test_exasol_tools.lua
exasol/analytics/lua/test/test_query_handler_runner.lua
exasol/analytics/lua/test/test_query_handler_runner_main.lua
exasol/analytics/lua/test/test_query_loop.lua
exasol/analytics/py.typed
exasol/analytics/query_handler/__init__.py
exasol/analytics/query_handler/context/__init__.py
exasol/analytics/query_handler/context/connection_name.py
exasol/analytics/query_handler/context/connection_name_proxy.py
exasol/analytics/query_handler/context/proxy/__init__.py
exasol/analytics/query_handler/context/proxy/bucketfs_location_proxy.py
exasol/analytics/query_handler/context/proxy/db_object_name_proxy.py
exasol/analytics/query_handler/context/proxy/db_object_name_with_schema_proxy.py
exasol/analytics/query_handler/context/proxy/drop_udf_query.py
exasol/analytics/query_handler/context/proxy/object_proxy.py
exasol/analytics/query_handler/context/proxy/table_like_name_proxy.py
exasol/analytics/query_handler/context/proxy/table_name.py
exasol/analytics/query_handler/context/proxy/udf_name.py
exasol/analytics/query_handler/context/proxy/view_name_proxy.py
exasol/analytics/query_handler/context/query_handler_context.py
exasol/analytics/query_handler/context/scope.py
exasol/analytics/query_handler/context/top_level_query_handler_context.py
exasol/analytics/query_handler/deployment/aaf_exasol_lua_script_generator.py
exasol/analytics/query_handler/deployment/constants.py
exasol/analytics/query_handler/deployment/deploy.py
exasol/analytics/query_handler/deployment/exasol_lua_script_generator.py
exasol_advanced_analytics_framework-0.6.2.dist-info/LICENSE
exasol_advanced_analytics_framework-0.6.2.dist-info/METADATA
exasol_advanced_analytics_framework-0.6.2.dist-info/WHEEL
exasol_advanced_analytics_framework-0.6.2.dist-info/RECORD
