Metadata-Version: 2.3
Name: exasol-advanced-analytics-framework
Version: 0.6.2
Summary: Framework for building complex data analysis algorithms with Exasol
Keywords: exasol
Author: Umit Buyuksahin
Author-email: umit.buyuksahin@exasol.com
Requires-Python: >=3.10,<4
Classifier: Programming Language :: Python :: 3
Classifier: Programming Language :: Python :: 3.10
Classifier: Programming Language :: Python :: 3.11
Classifier: Programming Language :: Python :: 3.12
Classifier: Programming Language :: Python :: 3.13
Requires-Dist: click (>=8.1.8,<9.0.0)
Requires-Dist: exasol-bucketfs (>=1.0.1,<3)
Requires-Dist: importlib-resources (>=6.5.2,<7.0.0)
Requires-Dist: jinja2 (>=3.1.6,<4.0.0)
Requires-Dist: joblib (>=1.4.2,<2.0.0)
Requires-Dist: nox (>=2025.2.9,<2026.0.0)
Requires-Dist: pandas (>=2.2.3,<3.0.0)
Requires-Dist: pydantic (>=2.10.6,<3.0.0)
Requires-Dist: pyexasol (>=0.25.0,<2)
Requires-Dist: pyzmq (>=26.2.1,<27.0.0)
Requires-Dist: sortedcontainers (>=2.4.0,<3.0.0)
Requires-Dist: structlog (>=25.1.0,<25.5)
Requires-Dist: typeguard (>=4.4.1,<5.0.0)
Project-URL: Homepage, https://github.com/exasol/advanced-analytics-framework
Project-URL: Repository, https://github.com/exasol/advanced-analytics-framework
